{
  "window_hours": 24,
  "new_level_life_hours": 8,
  "fetched_at_utc": "2026-06-15T16:18:36.953685+00:00",
  "fetched_at_est": "2026-06-15T12:18:36.953697-04:00",
  "last_new_level_added_at_est": "2026-06-15T12:11:02-04:00",
  "todays_new_levels": [
    {
      "price": 7620.0,
      "side": "bull",
      "added_at_est": "2026-06-15T09:13:03-04:00",
      "expires_at_est": "2026-06-15T17:13:03-04:00",
      "from_tweet_id": "2066509292992123287"
    },
    {
      "price": 7689.0,
      "side": "bull",
      "added_at_est": "2026-06-15T12:11:02-04:00",
      "expires_at_est": "2026-06-15T20:11:02-04:00",
      "from_tweet_id": "2066554080223195285"
    }
  ],
  "updates": [
    {
      "tweet_id": "2066211258588631522",
      "timestamp_utc": "2026-06-14T17:28:47.000Z",
      "timestamp_est": "2026-06-14T13:28:47-04:00",
      "tweet_text": "@NehaPat45471369 At 6pm tonight tradingview will open with the new levels, so it will sync up with the new levels",
      "added_bull_levels": [],
      "added_bear_levels": [],
      "notes": "Reply to user about TradingView update timing. No price mentioned, no actionable level named."
    },
    {
      "tweet_id": "2066211346354463172",
      "timestamp_utc": "2026-06-14T17:29:07.000Z",
      "timestamp_est": "2026-06-14T13:29:07-04:00",
      "tweet_text": "@NehaPat45471369 from newsletter. So don't need to do anything now!",
      "added_bull_levels": [],
      "added_bear_levels": [],
      "notes": "Reply tweet with no price levels mentioned, purely conversational reference to newsletter with no actionable prices."
    },
    {
      "tweet_id": "2066240239362842762",
      "timestamp_utc": "2026-06-14T19:23:56.000Z",
      "timestamp_est": "2026-06-14T15:23:56-04:00",
      "tweet_text": "The hardest part of trading isnt trading, its waiting. The market will present at least 1 high win rate, planned, A+ setup daily. But you have to wait for it, and not take all the 50/50 boredom trades that will eat the profit from the A+ trade before it even hits. Less=more",
      "added_bull_levels": [],
      "added_bear_levels": [],
      "notes": "Pure trading philosophy/mindset commentary. No prices mentioned, no actionable levels named."
    },
    {
      "tweet_id": "2066490251166552149",
      "timestamp_utc": "2026-06-15T11:57:24.000Z",
      "timestamp_est": "2026-06-15T07:57:24-04:00",
      "tweet_text": "Huge follow through in #ES_F: Last Wednesday we got long on the 7311 Failed Breakdown. All week, I had one target I repeated 5x times daily: 7590. We finally hit last eve, for +279 points.\n\nPlan today: Work done, ride runner. 7611, 7620, 7639 bonus. 7590, 7570=micro supports https://t.co/lKiQdxpBbb",
      "added_bull_levels": [],
      "added_bear_levels": [],
      "notes": "All prices (7311, 7590, 7611, 7639, 7570) are morning-plan levels or hindsight references. 7620 appears in a directional list of existing targets, no new naming language."
    },
    {
      "tweet_id": "2066490292753031632",
      "timestamp_utc": "2026-06-15T11:57:33.000Z",
      "timestamp_est": "2026-06-15T07:57:33-04:00",
      "tweet_text": "NOTE: ES is rolling over from June 2026 front month (ESM2026) to September front month contract (ESU2026).  These levels are now all September. June will expire Friday June 19th and stop trading completely but as the week goes on volume will transfer to September",
      "added_bull_levels": [],
      "added_bear_levels": [],
      "notes": "Tweet is a contract rollover administrative notice (June\u2192September ESU2026). No actionable price levels named; purely informational."
    },
    {
      "tweet_id": "2066491092267073750",
      "timestamp_utc": "2026-06-15T12:00:44.000Z",
      "timestamp_est": "2026-06-15T08:00:44-04:00",
      "tweet_text": "@JA28970348 63 points higher for September",
      "added_bull_levels": [],
      "added_bear_levels": [],
      "notes": "Conversational reply referencing a point differential for September \u2014 no actionable price named, no naming language, purely informational math commentary."
    },
    {
      "tweet_id": "2066493532957782369",
      "timestamp_utc": "2026-06-15T12:10:26.000Z",
      "timestamp_est": "2026-06-15T08:10:26-04:00",
      "tweet_text": "@YawningKitty24 That's why its called a magnet! Probably 95% of the time they hit (but it won't be in a straight line). One of the better trades this year",
      "added_bull_levels": [],
      "added_bear_levels": [],
      "notes": "Conversational reply about magnet targets hitting; no price named, no actionable level introduced."
    },
    {
      "tweet_id": "2066494262309466164",
      "timestamp_utc": "2026-06-15T12:13:20.000Z",
      "timestamp_est": "2026-06-15T08:13:20-04:00",
      "tweet_text": "@Pete66668332642 I didn't, I havn't traded since Wednesday!",
      "added_bull_levels": [],
      "added_bear_levels": [],
      "notes": "Casual reply to a user about trading activity; no price levels named or actionable information provided."
    },
    {
      "tweet_id": "2066501201072378220",
      "timestamp_utc": "2026-06-15T12:40:54.000Z",
      "timestamp_est": "2026-06-15T08:40:54-04:00",
      "tweet_text": "@livezey954181 They're not supports I'd engage but I still throw them out there for people who may want to. I only trade if we get a deep elevator down sell and failed breakdown. Once we get volatility I start posting actual entries not just supporrts",
      "added_bull_levels": [],
      "added_bear_levels": [],
      "notes": "No prices named at all; purely meta-commentary about trading style and when he posts entries. No actionable level introduced."
    },
    {
      "tweet_id": "2066501497689395228",
      "timestamp_utc": "2026-06-15T12:42:05.000Z",
      "timestamp_est": "2026-06-15T08:42:05-04:00",
      "tweet_text": "@atlasbtcgrowth A dip is always healthy/bullish. Have to thing the opposite of what retail traders think. When they see red they think its bearish and the market is topping, but the reality is more red in an uptrend=healthier and more continued upside later",
      "added_bull_levels": [],
      "added_bear_levels": [],
      "notes": "Pure educational/philosophical commentary on market psychology. No price levels named, no actionable entries, targets, or triggers mentioned."
    },
    {
      "tweet_id": "2066509292992123287",
      "timestamp_utc": "2026-06-15T13:13:03.000Z",
      "timestamp_est": "2026-06-15T09:13:03-04:00",
      "tweet_text": "We finally got to my macro target/magnet of 7590 after a +279 point long from Wednesday's 7311 Failed Breakdown. 7590 backtests the June 5th breakdown. Now, there is nothing to trade until the next deep bear trap. Ride runner\n\n7590 (testing), 7570=supports. 7611, 7620, 7639 bonus https://t.co/u4dy5TZX9g",
      "added_bull_levels": [
        7620.0
      ],
      "added_bear_levels": [],
      "notes": "7620 named as bonus resistance target not in morning plan; 7590/7570/7611/7639 are all existing morning-plan levels."
    },
    {
      "tweet_id": "2066509321484009812",
      "timestamp_utc": "2026-06-15T13:13:10.000Z",
      "timestamp_est": "2026-06-15T09:13:10-04:00",
      "tweet_text": "NOTE: ES is rolling over from June 2026 front month (ESM2026) to September front month contract (ESU2026).  These levels are now all September. June will expire Friday June 19th and stop trading completely but as the week goes on volume will transfer to September",
      "added_bull_levels": [],
      "added_bear_levels": [],
      "notes": "Tweet is an administrative note about contract rollover from ESM2026 to ESU2026; no actionable prices named, no new levels introduced."
    },
    {
      "tweet_id": "2066519469698978205",
      "timestamp_utc": "2026-06-15T13:53:30.000Z",
      "timestamp_est": "2026-06-15T09:53:30-04:00",
      "tweet_text": "We are nicely running today's set of targets in #ES_F. All last week my macro target was 7590, repeated 4-5x daily. We hit it last eve after a 279 point run.\n\nToday 1st support was 7590 (held). Targets I gave were 7611 (hit), 7620 (hit), 7639 next. Ride your runner from last week https://t.co/uvCdzIFtiN",
      "added_bull_levels": [],
      "added_bear_levels": [],
      "notes": "All prices mentioned (7590, 7611, 7620, 7639) are morning-plan levels or hindsight references to already-hit targets. No new actionable levels introduced."
    },
    {
      "tweet_id": "2066519827959664675",
      "timestamp_utc": "2026-06-15T13:54:55.000Z",
      "timestamp_est": "2026-06-15T09:54:55-04:00",
      "tweet_text": "@ES_Money_Print I don't short any levels period! We're not in a downtrend though, but I'd be a little surprised if we just cleanly headed to ATHs now. I suspect we;re probably going to start a consolidation phase for a while then put in the next 500-1000 point later in the year",
      "added_bull_levels": [],
      "added_bear_levels": [],
      "notes": "Pure directional commentary/opinion about consolidation and ATHs. No specific actionable price levels named whatsoever."
    },
    {
      "tweet_id": "2066520077902520337",
      "timestamp_utc": "2026-06-15T13:55:55.000Z",
      "timestamp_est": "2026-06-15T09:55:55-04:00",
      "tweet_text": "@MizuTraderr None, we got the volatility last Wednesday now bears need to pay for that until the next big flush so we can do it again",
      "added_bull_levels": [],
      "added_bear_levels": [],
      "notes": "Pure market commentary/opinion with no price levels named at all. No actionable entry, exit, support, or resistance mentioned."
    },
    {
      "tweet_id": "2066521043020226892",
      "timestamp_utc": "2026-06-15T13:59:45.000Z",
      "timestamp_est": "2026-06-15T09:59:45-04:00",
      "tweet_text": "NOTE: ES is rolling over from June 2026 front month (ESM2026) to September front month contract (ESU2026).  These levels are now all September. June will expire Friday June 19th and stop trading completely but as the week goes on volume will transfer to September",
      "added_bull_levels": [],
      "added_bear_levels": [],
      "notes": "Tweet is an administrative rollover notice (ESM2026->ESU2026). No actionable prices named, no new levels introduced."
    },
    {
      "tweet_id": "2066521430540394967",
      "timestamp_utc": "2026-06-15T14:01:17.000Z",
      "timestamp_est": "2026-06-15T10:01:17-04:00",
      "tweet_text": "@RedPill51762365 Have to wait for the next selloff unfortunately. I havnt had a new trade since last Wednesday",
      "added_bull_levels": [],
      "added_bear_levels": [],
      "notes": "Conversational reply to a user; no prices mentioned, no actionable levels named."
    },
    {
      "tweet_id": "2066521833449324864",
      "timestamp_utc": "2026-06-15T14:02:53.000Z",
      "timestamp_est": "2026-06-15T10:02:53-04:00",
      "tweet_text": "@WestNyc1 There was a small chance it didn't but probably 90-95% of the time those backtest levels become magnets and we get there eventually",
      "added_bull_levels": [],
      "added_bear_levels": [],
      "notes": "Conversational reply about probability of backtests becoming magnets; no specific price named or actionable level introduced."
    },
    {
      "tweet_id": "2066526997912682966",
      "timestamp_utc": "2026-06-15T14:23:25.000Z",
      "timestamp_est": "2026-06-15T10:23:25-04:00",
      "tweet_text": "@WestNyc1 And it definitely took the max pain path, came 35 points shy on the 9th, trapped bulls, made a new low, trapped bears, then came here",
      "added_bull_levels": [],
      "added_bear_levels": [],
      "notes": "Pure price action observation/narrative about prior movement \u2014 no actionable price named, no naming language, no new level introduced."
    },
    {
      "tweet_id": "2066532475078152430",
      "timestamp_utc": "2026-06-15T14:45:11.000Z",
      "timestamp_est": "2026-06-15T10:45:11-04:00",
      "tweet_text": "Slow grind continues in #ES_F and 0 to do but ride runner until we get volatility. My macro target all last week was 7590 to backtest the June 5th breakdown. We hit yesterday, cleared. This AM, 7590 became support (held). Targets were 7611 (hit), 7620 (hit), 7639.\n\n7590=support https://t.co/DaLu9BZceU",
      "added_bull_levels": [],
      "added_bear_levels": [],
      "notes": "All prices mentioned (7590, 7611, 7620, 7639) are either morning-plan levels or hindsight observations of targets already hit; no new actionable levels introduced."
    },
    {
      "tweet_id": "2066532499472134453",
      "timestamp_utc": "2026-06-15T14:45:16.000Z",
      "timestamp_est": "2026-06-15T10:45:16-04:00",
      "tweet_text": "NOTE: ES is rolling over from June 2026 front month (ESM2026) to September front month contract (ESU2026).  These levels are now all September. June will expire Friday June 19th and stop trading completely but as the week goes on volume will transfer to September",
      "added_bull_levels": [],
      "added_bear_levels": [],
      "notes": "Tweet is purely informational about contract rollover from ESM2026 to ESU2026. No actionable prices named, no new levels introduced."
    },
    {
      "tweet_id": "2066554080223195285",
      "timestamp_utc": "2026-06-15T16:11:02.000Z",
      "timestamp_est": "2026-06-15T12:11:02-04:00",
      "tweet_text": "All targets complete for today in #ES_F. We got long last Wed on the 7310 Failed Breakdown. My target for this long was 7590. Hit last eve, cleared. It then became support this morning. Todays slate of given targets 8am were 7611 (hit), 7620 (hit), 7639 (done).\n\n7660, 7689 next https://t.co/XCufQ6LTMP",
      "added_bull_levels": [
        7689.0
      ],
      "added_bear_levels": [],
      "notes": "7689 named explicitly as 'next' target alongside 7660 (morning plan). 7660 is already in plan; 7689 is new and actionable as next bull target."
    },
    {
      "tweet_id": "2066554154546340249",
      "timestamp_utc": "2026-06-15T16:11:19.000Z",
      "timestamp_est": "2026-06-15T12:11:19-04:00",
      "tweet_text": "NOTE: ES is rolling over from June 2026 front month (ESM2026) to September front month contract (ESU2026).  These levels are now all September. June will expire Friday June 19th and stop trading completely but as the week goes on volume will transfer to September",
      "added_bull_levels": [],
      "added_bear_levels": [],
      "notes": "Tweet is an administrative note about contract rollover from ESM2026 to ESU2026. No actionable price levels named whatsoever."
    },
    {
      "tweet_id": "2066554253456355655",
      "timestamp_utc": "2026-06-15T16:11:43.000Z",
      "timestamp_est": "2026-06-15T12:11:43-04:00",
      "tweet_text": "@br71217_brad Done!",
      "added_bull_levels": [],
      "added_bear_levels": [],
      "notes": "Tweet is a one-word reply '@br71217_brad Done!' \u2014 no price levels, no actionable language, no naming language whatsoever."
    },
    {
      "tweet_id": "2066555302271488457",
      "timestamp_utc": "2026-06-15T16:15:53.000Z",
      "timestamp_est": "2026-06-15T12:15:53-04:00",
      "tweet_text": "@EpicCharting Havnt had a trade since last Wednesday. Might be another day ir two at this rate!",
      "added_bull_levels": [],
      "added_bear_levels": [],
      "notes": "Casual conversational reply about trading inactivity; no price levels named or implied whatsoever."
    }
  ]
}
