{
  "window_hours": 24,
  "new_level_life_hours": 8,
  "fetched_at_utc": "2026-07-21T19:32:52.330698+00:00",
  "fetched_at_est": "2026-07-21T15:32:52.330703-04:00",
  "last_new_level_added_at_est": "2026-07-21T09:22:17-04:00",
  "todays_new_levels": [
    {
      "price": 7522.0,
      "side": "bull",
      "added_at_est": "2026-07-21T09:22:17-04:00",
      "expires_at_est": "2026-07-21T17:22:17-04:00",
      "from_tweet_id": "2079557579781423198"
    }
  ],
  "updates": [
    {
      "tweet_id": "2079536198897324330",
      "timestamp_utc": "2026-07-21T11:57:20.000Z",
      "timestamp_est": "2026-07-21T07:57:20-04:00",
      "tweet_text": "Evening traders gifted with yet another long in #ES_F, just like Sunday. Same drill daily. Per newsletter, recoveries of the 7490 2 day shelf were actionable. We got it last evening, went +37\n\nPlan today: Ride runner until vol expands. 7522, 7532, 7548 next set. 7490=support https://t.co/02HqiWQHKX",
      "added_bull_levels": [],
      "added_bear_levels": [],
      "notes": "7522 is the only unlisted price, but it appears in a directional target list referencing the newsletter/morning plan context, not introduced with naming language as a standalone new level."
    },
    {
      "tweet_id": "2079557579781423198",
      "timestamp_utc": "2026-07-21T13:22:17.000Z",
      "timestamp_est": "2026-07-21T09:22:17-04:00",
      "tweet_text": "Volatility has died out again in #ES_F and everyone knows the drill now. Sit in runner, do nothing until the next bear trap. Per newsletter recovery of the 7490 shelf triggered long last evening. Targets are now 7522, 7532, 7548, then onto 7575 which still needs to backtest https://t.co/2xS5UC1Sx4",
      "added_bull_levels": [
        7522.0
      ],
      "added_bear_levels": [],
      "notes": "7522 is named as an explicit upside target not in the morning plan. 7532, 7548, 7575 are morning-plan reaffirmations."
    },
    {
      "tweet_id": "2079572775233003576",
      "timestamp_utc": "2026-07-21T14:22:40.000Z",
      "timestamp_est": "2026-07-21T10:22:40-04:00",
      "tweet_text": "@kevinc2114 Double bottomed it exact. Could still take the long there sometimes price does that (it did it last week also). Double bottoms the low exact but doesn't get that one tick extra needed for a Failed Breakdown",
      "added_bull_levels": [],
      "added_bear_levels": [],
      "notes": "Reply explaining price action (double bottom, failed breakdown) \u2014 no new actionable price named, pure observation/commentary."
    },
    {
      "tweet_id": "2079579638762729940",
      "timestamp_utc": "2026-07-21T14:49:57.000Z",
      "timestamp_est": "2026-07-21T10:49:57-04:00",
      "tweet_text": "Finally unpinning from the morning chop in #ES_F mildly and little to do now but ride runner until next bear trap. 7490 shelf recovery was last entry. Today's targets were 7522 (hit), 7532 (hit), 7548 next, then 7575 which has to backtest still and has been unable to so far https://t.co/TpSv7f6CV1",
      "added_bull_levels": [],
      "added_bear_levels": [],
      "notes": "All prices mentioned (7490, 7522, 7532, 7548, 7575) are morning-plan levels or hit-target observations; no new actionable levels named."
    },
    {
      "tweet_id": "2079584006148895090",
      "timestamp_utc": "2026-07-21T15:07:18.000Z",
      "timestamp_est": "2026-07-21T11:07:18-04:00",
      "tweet_text": "@Vinsmoke1P Means the market is extremely weak if it can't complete those basic backtests",
      "added_bull_levels": [],
      "added_bear_levels": [],
      "notes": "Pure directional commentary about market weakness; no price named, no actionable level introduced."
    },
    {
      "tweet_id": "2079600906773877142",
      "timestamp_utc": "2026-07-21T16:14:27.000Z",
      "timestamp_est": "2026-07-21T12:14:27-04:00",
      "tweet_text": "One way traffic in #ES_F and summer trading usually gives an entry, then trends up for 1-3 days with nothing to do but ride runner. 7490 reclaim was last entry. Targets given at 8am were fourfold: 7522 (hit), 7532 (hit), 7548 (almost), then the big 7575 backtest. Decision point https://t.co/zxvbCrPMJQ",
      "added_bull_levels": [],
      "added_bear_levels": [],
      "notes": "All prices mentioned (7490, 7522, 7532, 7548, 7575) are morning-plan levels or hit-targets; tweet is hindsight recap of existing levels, no new actionable levels named."
    },
    {
      "tweet_id": "2079622579661283729",
      "timestamp_utc": "2026-07-21T17:40:35.000Z",
      "timestamp_est": "2026-07-21T13:40:35-04:00",
      "tweet_text": "Little going on now in #ES_F but levels respecting well. After the 7490 Failed Breakdown long given in newsletter, today's targets were 4 fold and given at 8am: 7522 (hit), 7532 (hit), 7548 (hit - stuck here for 1hr). Just 7575 yet, this is the major backtest to complete this leg https://t.co/oBKRlMtxDw",
      "added_bull_levels": [],
      "added_bear_levels": [],
      "notes": "All prices mentioned (7490, 7522, 7532, 7548, 7575) are either morning-plan levels or hindsight references to targets already given at 8am. No new actionable level introduced."
    },
    {
      "tweet_id": "2079635713570525403",
      "timestamp_utc": "2026-07-21T18:32:46.000Z",
      "timestamp_est": "2026-07-21T14:32:46-04:00",
      "tweet_text": "@ebin59843030 Just look at price, its very obvious when its volatile or not volatile",
      "added_bull_levels": [],
      "added_bear_levels": [],
      "notes": "Pure conversational reply about reading price/volatility; no price named, no actionable level of any kind."
    },
    {
      "tweet_id": "2079643511314337892",
      "timestamp_utc": "2026-07-21T19:03:45.000Z",
      "timestamp_est": "2026-07-21T15:03:45-04:00",
      "tweet_text": "@D5star_general Quite a few newsletter setups we got! ~72 near Failed Breakdown, 90 reclaim, 06 reclaim, 32 reclaim",
      "added_bull_levels": [],
      "added_bear_levels": [],
      "notes": "All references (7272, 7290, 7306, 7332) are hindsight recaps of newsletter setups already triggered \u2014 no new actionable levels named."
    },
    {
      "tweet_id": "2079643906652725753",
      "timestamp_utc": "2026-07-21T19:05:19.000Z",
      "timestamp_est": "2026-07-21T15:05:19-04:00",
      "tweet_text": "Closing update #ES_F: No volatility. 4 targets were given for today. 7522 (hit), 7532 (hit), 7548 (hit). We've been stuck at this 7548 level now for over 2 hours and ES clearly likes it. 7575 is next. Then we head to 7627. Newsletter out shortly talking the next entries from here",
      "added_bull_levels": [],
      "added_bear_levels": [],
      "notes": "All prices mentioned (7522, 7532, 7548, 7575, 7627) are either morning-plan levels or hit-target observations. No new actionable levels named."
    }
  ]
}
