{
  "window_hours": 24,
  "new_level_life_hours": 8,
  "fetched_at_utc": "2026-05-31T15:24:17.304198+00:00",
  "fetched_at_est": "2026-05-31T11:24:17.304205-04:00",
  "last_new_level_added_at_est": "",
  "todays_new_levels": [],
  "updates": [
    {
      "tweet_id": "2060746190719799415",
      "timestamp_utc": "2026-05-30T15:32:33.000Z",
      "timestamp_est": "2026-05-30T11:32:33-04:00",
      "tweet_text": "@RicoElite Probbaly interactive brokers!",
      "added_bull_levels": [],
      "added_bear_levels": [],
      "notes": "Tweet is a casual reply about a broker recommendation; no price levels mentioned or implied."
    },
    {
      "tweet_id": "2060827026588578024",
      "timestamp_utc": "2026-05-30T20:53:46.000Z",
      "timestamp_est": "2026-05-30T16:53:46-04:00",
      "tweet_text": "@atlasbtcgrowth Most likely yes",
      "added_bull_levels": [],
      "added_bear_levels": [],
      "notes": "Reply tweet with no price levels named; purely conversational response."
    }
  ]
}
