{
  "window_hours": 24,
  "new_level_life_hours": 8,
  "fetched_at_utc": "2026-06-26T00:13:46.859355+00:00",
  "fetched_at_est": "2026-06-25T20:13:46.859360-04:00",
  "last_new_level_added_at_est": "",
  "todays_new_levels": [],
  "updates": [
    {
      "tweet_id": "2070110946463305801",
      "timestamp_utc": "2026-06-25T11:44:45.000Z",
      "timestamp_est": "2026-06-25T07:44:45-04:00",
      "tweet_text": "Yesterday's newsletter was sent early at 2:50PM in preparation for a long in #ES_F: The Failed Breakdown of the 7408 low. At 3:08PM, we swept 7408 to 7405, recovered, &amp; longed. We are +70\n\nPlan today: Ride runner until next bear trap. 7492, 7510, 7530 magnet next. 39/25=supports https://t.co/KuDChg5WnJ",
      "added_bull_levels": [],
      "added_bear_levels": [],
      "notes": "All prices mentioned (7408/7405=hindsight trade, 7492/7510/7530/7439/7425=morning plan levels) are existing plan levels or historical references. 7492 not in plan but framed as runner target/magnet, not a new named actionable level with naming language."
    },
    {
      "tweet_id": "2070113127681651058",
      "timestamp_utc": "2026-06-25T11:53:25.000Z",
      "timestamp_est": "2026-06-25T07:53:25-04:00",
      "tweet_text": "@CorlukaDejan That would count, but not something I'd take (I won't trade today unless we lose yesterday's low)",
      "added_bull_levels": [],
      "added_bear_levels": [],
      "notes": "No price level named; purely a conditional/behavioral statement about trading intent with no actionable price cited."
    },
    {
      "tweet_id": "2070113240525201693",
      "timestamp_utc": "2026-06-25T11:53:52.000Z",
      "timestamp_est": "2026-06-25T07:53:52-04:00",
      "tweet_text": "@CorlukaDejan I am very strict though with my entries and won't take a Failed Breakdown unless its basically 100% win rate which means I need to wait for huge volatility expansions",
      "added_bull_levels": [],
      "added_bear_levels": [],
      "notes": "Reply explaining entry discipline for Failed Breakdowns; no price levels named or actionable triggers given."
    },
    {
      "tweet_id": "2070131574113226946",
      "timestamp_utc": "2026-06-25T13:06:43.000Z",
      "timestamp_est": "2026-06-25T09:06:43-04:00",
      "tweet_text": "There's 7492 1st target hit in #ES_F. Nothing to do now at all. Last entry was after 3pm yesterday: The Failed Breakdown of 7408. We swept it, recovered, got long, went +70. 7510, 7530 remain next. 7530 is a magnet from here as posted all week.\n\nNo change to supports https://t.co/uV1XlNWu1V",
      "added_bull_levels": [],
      "added_bear_levels": [],
      "notes": "7492 is a target hit (observation), 7510/7530 are reaffirmations of morning plan or prior posts, no new actionable levels named."
    },
    {
      "tweet_id": "2070141013373436329",
      "timestamp_utc": "2026-06-25T13:44:13.000Z",
      "timestamp_est": "2026-06-25T09:44:13-04:00",
      "tweet_text": "Nothing to do still in #ES_F. Last long entry was 3:18PM yesterday on the 7408 low Failed Breakdown. We ran to 7492 target this morning, dipped. Now, sit on hands until the next big bear trap.\n\nReclaims of 52 now are a low quality entry to 72, 85, 92.\n\n7439/7425= weak supports https://t.co/NpGdiJJZzd",
      "added_bull_levels": [],
      "added_bear_levels": [],
      "notes": "All prices mentioned (7408, 7492, 7452, 7472, 7485, 7492, 7439, 7425) are morning-plan levels or observations/trade management references, not new actionable levels."
    },
    {
      "tweet_id": "2070141868453630010",
      "timestamp_utc": "2026-06-25T13:47:37.000Z",
      "timestamp_est": "2026-06-25T09:47:37-04:00",
      "tweet_text": "@NorthoverDaniel @CorlukaDejan I keep my size mostly the same as it keeps emotions in control, but yes I've become very selective. There's no way to have a high win rate unless your sniping, typically no more than one trade a trade a day, if that. Best day traders I've known are doing 1-2 scalps per week",
      "added_bull_levels": [],
      "added_bear_levels": [],
      "notes": "Pure conversational reply about trading style/frequency. No prices mentioned, no actionable levels named."
    },
    {
      "tweet_id": "2070142487302222225",
      "timestamp_utc": "2026-06-25T13:50:05.000Z",
      "timestamp_est": "2026-06-25T09:50:05-04:00",
      "tweet_text": "Note: Watch for reclaims of 7425 now or Failed Breakdowns of yesterday's daily low",
      "added_bull_levels": [],
      "added_bear_levels": [],
      "notes": "7425 is already in the morning plan; 'yesterday's daily low' is unnamed/unpriced. No new actionable level introduced."
    },
    {
      "tweet_id": "2070143983557160992",
      "timestamp_utc": "2026-06-25T13:56:01.000Z",
      "timestamp_est": "2026-06-25T09:56:01-04:00",
      "tweet_text": "We are finally getting today's volatility expansion, which means we can stalk entries. I only trade on vol expansions. Last long was the 3:18PM 7408 Failed Breakdown that took us to 7492 target in #ES_F.\n\nWatch recoveries of 7405 now to trigger to 7425+. 7383, 7365 are below now https://t.co/XKIMWRJWt9",
      "added_bull_levels": [
        7405.0
      ],
      "added_bear_levels": [
        7383.0
      ],
      "notes": "7405 named as new bull trigger ('watch recoveries of 7405 now to trigger to 7425+'); 7383 named as new bear support below. 7365/7425 are morning-plan levels."
    },
    {
      "tweet_id": "2070145128233066875",
      "timestamp_utc": "2026-06-25T14:00:34.000Z",
      "timestamp_est": "2026-06-25T10:00:34-04:00",
      "tweet_text": "@CorlukaDejan When I say bears control in the newsletter I just mean we should expect bounces to have trouble sustaining. We will still get great bounces though. The best longs are when bears control",
      "added_bull_levels": [],
      "added_bear_levels": [],
      "notes": "No price levels named at all; purely directional/contextual commentary explaining market bias and bounce expectations."
    },
    {
      "tweet_id": "2070146659284033970",
      "timestamp_utc": "2026-06-25T14:06:39.000Z",
      "timestamp_est": "2026-06-25T10:06:39-04:00",
      "tweet_text": "There's today's trade complete in #ES_F. Close up platform. Same boring drill everyday. 1) Wait for vol expasion 2) Wait for Failed Breakdown. 3) Take out points. 7405 recovery was long trigger. Targets were 7425 (hit), 7439 (hit). 7453, 7492+ if ES wants more\n\nRide runner now https://t.co/XZEaDwOMzT",
      "added_bull_levels": [
        7453.0,
        7492.0
      ],
      "added_bear_levels": [],
      "notes": "7453 and 7492 named as new upside targets beyond morning-plan levels; 7405/7425/7439 are morning-plan reaffirmations."
    },
    {
      "tweet_id": "2070147586556678163",
      "timestamp_utc": "2026-06-25T14:10:20.000Z",
      "timestamp_est": "2026-06-25T10:10:20-04:00",
      "tweet_text": "@BrianMelcher24 Not a problem! Yes most boring job on the planet (ES just repeats the same cycles over and over, and the trades are all the exact same as well). But twitter and newsletter keeps me busy!",
      "added_bull_levels": [],
      "added_bear_levels": [],
      "notes": "Pure conversational reply; no price levels named, no actionable language, no new levels of any kind."
    },
    {
      "tweet_id": "2070150867106279460",
      "timestamp_utc": "2026-06-25T14:23:22.000Z",
      "timestamp_est": "2026-06-25T10:23:22-04:00",
      "tweet_text": "@Mcloud4004 @BrianMelcher24 Appreciate it, and thanks for the subscribe!",
      "added_bull_levels": [],
      "added_bear_levels": [],
      "notes": "Tweet is a social reply/thank-you with no price levels mentioned at all."
    },
    {
      "tweet_id": "2070158495266017443",
      "timestamp_utc": "2026-06-25T14:53:41.000Z",
      "timestamp_est": "2026-06-25T10:53:41-04:00",
      "tweet_text": "We continue to rip nicely in #ES_F. Today's long was the Failed Breakdown of yesterday's 7405 daily low, given live and for free. We swept it to 7392, recovered, and off we went. Targets were 7425 (hit), 7439 (hit), 7492, 7510, then 7530 next.\n\nPlatform closed now, ride runner https://t.co/Y08wmzot5L",
      "added_bull_levels": [],
      "added_bear_levels": [],
      "notes": "All prices mentioned (7392 sweep obs, 7425/7439/7492/7510/7530 targets) are observations of existing plan levels or trade management. No new actionable levels named."
    },
    {
      "tweet_id": "2070161292183158816",
      "timestamp_utc": "2026-06-25T15:04:48.000Z",
      "timestamp_est": "2026-06-25T11:04:48-04:00",
      "tweet_text": "@RChew1119 Tweeted here: Also was in newsletter though https://t.co/HqdVj4zyAI",
      "added_bull_levels": [],
      "added_bear_levels": [],
      "notes": "Tweet is a reply referencing a prior newsletter link \u2014 no price levels named, no actionable language, purely conversational/reference."
    },
    {
      "tweet_id": "2070177942202646985",
      "timestamp_utc": "2026-06-25T16:10:58.000Z",
      "timestamp_est": "2026-06-25T12:10:58-04:00",
      "tweet_text": "Sit on hands. 1-2x per day, #ES_F produces a large volatility expansion. That is the cue to trade. This then sets up a Failed Breakdown (today it was of the 7405 low, given live). Then, close platform. \n\nTargets were 7425, 7439 (both hit). 7472, 7492, 7510, 7530 next. 7530=magnet https://t.co/25nhLeOyDv",
      "added_bull_levels": [
        7472.0,
        7492.0
      ],
      "added_bear_levels": [],
      "notes": "7472 and 7492 are named as 'next' upside targets not in morning plan. 7425/7439/7510/7530 are morning-plan levels; omitted."
    },
    {
      "tweet_id": "2070178109001764934",
      "timestamp_utc": "2026-06-25T16:11:37.000Z",
      "timestamp_est": "2026-06-25T12:11:37-04:00",
      "tweet_text": "@hcooper0113 Yes. 7530 has to backtest still though, its a magnet. We're making our way up there slowly",
      "added_bull_levels": [],
      "added_bear_levels": [],
      "notes": "7530 is already in the morning plan; tweet is a conversational reaffirmation/observation of price action, not a new actionable level."
    },
    {
      "tweet_id": "2070185965834961298",
      "timestamp_utc": "2026-06-25T16:42:51.000Z",
      "timestamp_est": "2026-06-25T12:42:51-04:00",
      "tweet_text": "@ken717w Its not a question you need to answer! That's predicting. Wait on triggers, react with a trade, manage level to level",
      "added_bull_levels": [],
      "added_bear_levels": [],
      "notes": "No prices mentioned; purely instructional/conversational advice about trading approach. No actionable level named."
    },
    {
      "tweet_id": "2070188075641077947",
      "timestamp_utc": "2026-06-25T16:51:14.000Z",
      "timestamp_est": "2026-06-25T12:51:14-04:00",
      "tweet_text": "Little to do now but sit on hands in #ES_F. The long was the Failed Breakdown of yesterday's 7405 daily low. We ran +70. Targets were 7425, 7439 (both hit). 7472 (hit),7492, 7510, 7530 still above.\n\n7425-7492=a multiday chop range as we prep for trend https://t.co/zWDqrT1axy",
      "added_bull_levels": [],
      "added_bear_levels": [],
      "notes": "7472 and 7492 mentioned as targets but are observations of prior trade/hindsight refs; 7425/7439/7530 are morning-plan levels; 7472/7492 lack explicit actionable naming language."
    },
    {
      "tweet_id": "2070199615975051474",
      "timestamp_utc": "2026-06-25T17:37:05.000Z",
      "timestamp_est": "2026-06-25T13:37:05-04:00",
      "tweet_text": "We remain in a range 7425-7492 and back at range support now. The last long given was the 7405 Failed Breakdown of yesterday's low that paid 70 points. Now, just ride runner in #ES_F.\n\n7439, 7472, 7492 remain above. Then 7510, 7530 which is the magnet level that must test https://t.co/LT70JHQsAn",
      "added_bull_levels": [
        7472.0,
        7492.0
      ],
      "added_bear_levels": [],
      "notes": "7472 and 7492 named as resistance levels above; not in morning plan. 7439/7510/7530 are morning-plan reaffirmations."
    },
    {
      "tweet_id": "2070202384706384219",
      "timestamp_utc": "2026-06-25T17:48:05.000Z",
      "timestamp_est": "2026-06-25T13:48:05-04:00",
      "tweet_text": "@NerdRageDan Just chop now. Needs another deep flush to look good from here, ideally below the daily low",
      "added_bull_levels": [],
      "added_bear_levels": [],
      "notes": "No price named at all; purely directional commentary about needing a flush below daily low with no explicit actionable level cited."
    },
    {
      "tweet_id": "2070203472268464545",
      "timestamp_utc": "2026-06-25T17:52:24.000Z",
      "timestamp_est": "2026-06-25T13:52:24-04:00",
      "tweet_text": "@bigwood340 Much better! Just don't get this many setups when bulls control",
      "added_bull_levels": [],
      "added_bear_levels": [],
      "notes": "Pure conversational reply to a user; no price named, no actionable level, no naming language whatsoever."
    },
    {
      "tweet_id": "2070203794772619531",
      "timestamp_utc": "2026-06-25T17:53:41.000Z",
      "timestamp_est": "2026-06-25T13:53:41-04:00",
      "tweet_text": "@ooooopopppppp Yes 7510-7530. I suspect it probably defends and then we can spend a few weeks correcting (my hope at least since structure has flipped quite bearish) but as always we don't predict.",
      "added_bull_levels": [],
      "added_bear_levels": [],
      "notes": "7510-7530 range references already-published morning plan levels (7513, 7530); rest is directional commentary/opinion, no new actionable level named."
    },
    {
      "tweet_id": "2070209095785701874",
      "timestamp_utc": "2026-06-25T18:14:45.000Z",
      "timestamp_est": "2026-06-25T14:14:45-04:00",
      "tweet_text": "@DrJonnyBros We'd need to take out today's low and put in another big failed breakdown",
      "added_bull_levels": [],
      "added_bear_levels": [],
      "notes": "Reply describing a condition (take out today's low) with no explicit price named; pure directional commentary, not an actionable level."
    },
    {
      "tweet_id": "2070212329245909101",
      "timestamp_utc": "2026-06-25T18:27:36.000Z",
      "timestamp_est": "2026-06-25T14:27:36-04:00",
      "tweet_text": "As posted not much to do now, just ride your long runner. We got today's long at 10:18AM, given live. It was the Failed Breakdown of yesterday's 7405 daily low in #ES_F. Targets were 7439, 7472, 7492. 7421-7492=a chop range. Then, we break to 7510, 7530.\n\n7530 is a magnet https://t.co/qiuZ7unGzq",
      "added_bull_levels": [],
      "added_bear_levels": [],
      "notes": "All referenced prices (7439, 7530) are morning-plan levels; 7472/7492 are trade targets from earlier post; 7510 not named with actionable naming language \u2014 observation/chop commentary only."
    },
    {
      "tweet_id": "2070223393622827155",
      "timestamp_utc": "2026-06-25T19:11:34.000Z",
      "timestamp_est": "2026-06-25T15:11:34-04:00",
      "tweet_text": "Closing update #ES_F: Other than the 10:18AM 7405 Failed Breakdown, its been a no trade day as ES chops in the 7421-7492 chop range. Just hold your runner as we fill the range out. Newsletter out soon with next entries from here. 7530 remains the magnet",
      "added_bull_levels": [],
      "added_bear_levels": [],
      "notes": "7405 is trade management/hindsight ref to earlier FBD, 7421/7492 are chop range observations, 7530 is a morning plan reaffirmation. No new actionable levels named."
    }
  ]
}
